{
  "folder": "406_o2a5aa51a3d1d4b03acace461e648897b",
  "slug": "o2a5aa51a3d1d4b03acace461e648897b",
  "name": "名前が見つかりません",
  "logo": "https://image-financie.storage.googleapis.com/production/user/image/138514/user_icon_2025-11-21_10_52_24_%2B0000138514.jpeg",
  "history": [
    {
      "date": "20260604",
      "price": 0.0,
      "volume": 0.0,
      "members": 0,
      "stock": 0,
      "marketCap": 0,
      "active_ranking": "0"
    },
    {
      "date": "20260605",
      "price": 0.0,
      "volume": 0.0,
      "members": 99,
      "stock": 0,
      "marketCap": 0,
      "active_ranking": "-"
    },
    {
      "date": "20260606",
      "price": 0.0,
      "volume": 0.0,
      "members": 99,
      "stock": 0,
      "marketCap": 0,
      "active_ranking": "-"
    },
    {
      "date": "20260607",
      "price": 0.0,
      "volume": 0.0,
      "members": 99,
      "stock": 0,
      "marketCap": 0,
      "active_ranking": "-"
    },
    {
      "date": "20260608",
      "price": 0.0,
      "volume": 0.0,
      "members": 99,
      "stock": 0,
      "marketCap": 0,
      "active_ranking": "-"
    },
    {
      "date": "20260609",
      "price": 0.0,
      "volume": 0.0,
      "members": 99,
      "stock": 0,
      "marketCap": 0,
      "active_ranking": "-"
    },
    {
      "date": "20260610",
      "price": 0.0,
      "volume": 0.0,
      "members": 99,
      "stock": 0,
      "marketCap": 0,
      "active_ranking": "-"
    },
    {
      "date": "20260611",
      "price": 0.0,
      "volume": 0.0,
      "members": 99,
      "stock": 0,
      "marketCap": 0,
      "active_ranking": "-"
    },
    {
      "date": "20260612",
      "price": 0.0,
      "volume": 0.0,
      "members": 99,
      "stock": 0,
      "marketCap": 0,
      "active_ranking": "-"
    },
    {
      "date": "20260613",
      "price": 0.0,
      "volume": 0.0,
      "members": 99,
      "stock": 0,
      "marketCap": 0,
      "active_ranking": "-"
    },
    {
      "date": "20260614",
      "price": 0.0,
      "volume": 0.0,
      "members": 99,
      "stock": 0,
      "marketCap": 0,
      "active_ranking": "-"
    },
    {
      "date": "20260615",
      "price": 0.0,
      "volume": 0.0,
      "members": 99,
      "stock": 0,
      "marketCap": 0,
      "active_ranking": "-"
    },
    {
      "date": "20260616",
      "price": 0.0,
      "volume": 0.0,
      "members": 99,
      "stock": 0,
      "marketCap": 0,
      "active_ranking": "-"
    },
    {
      "date": "20260617",
      "price": 0.0,
      "volume": 0.0,
      "members": 99,
      "stock": 0,
      "marketCap": 0,
      "active_ranking": "-"
    },
    {
      "date": "20260618",
      "price": 0.0,
      "volume": 0.0,
      "members": 99,
      "stock": 0,
      "marketCap": 0,
      "active_ranking": "-"
    },
    {
      "date": "20260619",
      "price": 0.0,
      "volume": 0.0,
      "members": 99,
      "stock": 0,
      "marketCap": 0,
      "active_ranking": "-"
    },
    {
      "date": "20260620",
      "price": 0.0,
      "volume": 0.0,
      "members": 99,
      "stock": 0,
      "marketCap": 0,
      "active_ranking": "-"
    },
    {
      "date": "20260621",
      "price": 0.0,
      "volume": 0.0,
      "members": 99,
      "stock": 0,
      "marketCap": 0,
      "active_ranking": "-"
    },
    {
      "date": "20260622",
      "price": 0.0,
      "volume": 0.0,
      "members": 98,
      "stock": 0,
      "marketCap": 0,
      "active_ranking": "-"
    },
    {
      "date": "20260623",
      "price": 0.0,
      "volume": 0.0,
      "members": 98,
      "stock": 0,
      "marketCap": 0,
      "active_ranking": "-"
    },
    {
      "date": "20260624",
      "price": 0.0,
      "volume": 0.0,
      "members": 97,
      "stock": 0,
      "marketCap": 0,
      "active_ranking": "-"
    },
    {
      "date": "20260625",
      "price": 0.0,
      "volume": 0.0,
      "members": 97,
      "stock": 0,
      "marketCap": 0,
      "active_ranking": "-"
    },
    {
      "date": "20260626",
      "price": 0.0,
      "volume": 0.0,
      "members": 97,
      "stock": 0,
      "marketCap": 0,
      "active_ranking": "-"
    }
  ]
}